{
  "activos": [
    {
      "id": "1",
      "CodTransaccion": "",
      "NroFormulario": "",
      "idMarca": "",
      "idCategoria": "",
      "idTipo": "",
      "ValorUnitario": "",
      "idProveedor": "",
      "NroSerial": "",
      "idEmpresaResponsable": "",
      "idEstado": ""
    }
  ],
  "categoriaActivos": [
    { "id": "1", "Nombre": "equipo de computo" },
    { "id": "2", "Nombre": "electrodomestico" },
    { "id": "3", "Nombre": "juego" }
  ],
  "marcas": [
    { "id": "1", "Nombre": "lg" },
    { "id": "2", "Nombre": "compumax" },
    { "id": "3", "Nombre": "logitech" },
    { "id": "4", "Nombre": "benq" },
    { "id": "5", "Nombre": "asus" },
    { "id": "6", "Nombre": "lenovo" },
    { "id": "7", "Nombre": "hp" }
  ],
  "tipoPersonas": [
    {
      "id": "",
      "Nombre": ""
    }
  ],
  "tipoMovActivos": [
    {
      "id": "",
      "Nombre": ""
    }
  ],
  "tipoActivos": [
    { "id": "1", "Nombre": "monitor" },
    { "id": "2", "Nombre": "cpu" },
    { "id": "3", "Nombre": "teclado" },
    { "id": "4", "Nombre": "mouse" },
    { "id": "5", "Nombre": "aire acondicionado" },
    { "id": "6", "Nombre": "portatil" },
    { "id": "7", "Nombre": "impresora" }
  ],
  "estados": [
    { "id": "0", "Nombre": "no asignado" },
    { "id": "1", "Nombre": "asignado" },
    { "id": "2", "Nombre": "dado de baja por daño" },
    { "id": "3", "Nombre": "en reparación y/o garantia" }
  ],
  "proveedores": [
    {
      "id": "",
      "Nombre": "",
      "Email": ""
    }
  ],
  "historialActivos": [
    {
      "id": "",
      "idActivo": "",
      "Fecha": "",
      "idResponsable": "",
      "idEstado": ""
    }
  ],
  "telefonoPersonas": [
    {
      "id": "",
      "Nro": "",
      "ubicacion": "",
      "idPersona": ""
    }
  ],
  "asignaciones": [
    {
      "id": "",
      "Fecha": "",
      "idResponsable": ""
    }
  ],
  "personas": [
    {
      "id": "",
      "Nombre": "",
      "Email": "",
      "idTipoPersona": ""
    }
  ],
  "detalleMovimiento": [
    {
      "id": "",
      "Fecha": "",
      "idActivo": "",
      "Comentario": "",
      "idAsignacion": ""
    }
  ]
}
